pelican_publications/__init__.py
pelican_publications/publications.py
pelican_publications/version.py
pelican_publications-0.2.1.dist-info/WHEEL
pelican_publications-0.2.1.dist-info/metadata.json
pelican_publications-0.2.1.dist-info/RECORD
pelican_publications-0.2.1.dist-info/top_level.txt
pelican_publications-0.2.1.dist-info/DESCRIPTION.rst
pelican_publications-0.2.1.dist-info/METADATA
